pkggoorm/__init__.py
pkggoorm/pkggoormCode.py
pkggoorm-0.1.0.dist-info/licenses/LICENSE
pkggoorm-0.1.0.dist-info/METADATA
pkggoorm-0.1.0.dist-info/WHEEL
pkggoorm-0.1.0.dist-info/top_level.txt
pkggoorm-0.1.0.dist-info/RECORD
