Metadata-Version: 2.4
Name: pkggoorm
Version: 0.1.0
Summary: 설명 텍스트
Author-email: aks <example@gmail.com>
License: MIT License
Requires-Python: >=3.7
License-File: LICENSE
Dynamic: license-file
